tmug/__init__.py
tmug/__init__.pyi
tmug/__main__.py
tmug/main.py
tmug/py.typed
tmug/version.py
tmug-0.1.0.dist-info/LICENSE
tmug-0.1.0.dist-info/METADATA
tmug-0.1.0.dist-info/WHEEL
tmug-0.1.0.dist-info/entry_points.txt
tmug-0.1.0.dist-info/top_level.txt
tmug-0.1.0.dist-info/RECORD
