Metadata-Version: 2.1
Name: tmug
Version: 0.1.0
Summary: Make developer's life easier
Home-page: https://github.com/i386x/tmug
Author: Jiří Kučera
Author-email: sanczes@gmail.com
License: MIT
Project-URL: Bug Reports, https://github.com/i386x/tmug/issues
Project-URL: Source, https://github.com/i386x/tmug
Keywords: software development
Platform: any
Classifier: Development Status :: 1 - Planning
Classifier: Environment :: Console
Classifier: Intended Audience :: Developers
Classifier: License :: OSI Approved :: MIT License
Classifier: Operating System :: OS Independent
Classifier: Programming Language :: Python
Classifier: Programming Language :: Python :: 3
Classifier: Programming Language :: Python :: 3 :: Only
Classifier: Topic :: Software Development
Classifier: Topic :: Software Development :: Build Tools
Classifier: Topic :: Utilities
Requires-Python: <4,>=3.7
License-File: LICENSE
Provides-Extra: dev
Requires-Dist: check-manifest ; extra == 'dev'
Provides-Extra: test
Requires-Dist: coverage ; extra == 'test'
